[
    {
        "title": "BLOOD BANK MANAGEMENT SYSTEM",
        "description": "Developed a Blood Bank Management System by integrating ReactJS, Bootstrap, .Net Core and MSSQL for Backend as a service (BAAS) where Users can Post, Edit, Read, Delete the Blood Donations",
        "type": "Personal Projects",
        "imageUrl": "/assets/img/Blood Bank Management System.png",
        "githubUrl": "https://github.com/moirfan-dev/Blood-donation-bank",
        "skills": [
            "HTML",
            "BOOTSTRAP",
            "TYPESCRIPT",
            "REACT.JS",
            ".NET CORE",
            "ENTITY FRAMEWORK CORE",
            "MICROSOFT SQL SERVER"
        ]
    }
]
